backup/cablebridge.py
backup/cablebridge3.py
backup/cablebridge_base.py
backup/cablebridge_base3.py
backup/cablebridge_v1.py
backup/cablebridge_v3.py
backup/main.py
backup/mechanical.py
backup/run_env_di.py
backup/test_ans.py
backup/test_cable.py
backup/test_ops.py
backup/test_pistonball.py
backup/train_main.py
backup/cablebridge_di/envs/__init__.py
backup/cablebridge_di/envs/cablebridge_base.py
backup/cablebridge_di/envs/cablebridge_models.py
backup/cablebridge_di/envs/backup/cablebridge_base.py
backup/cablebridge_di/envs/backup/cablebridge_base2.py
backup/cablebridge_di/envs/backup/cablebridge_env.py
bridgezoo/__init__.py
bridgezoo/cablebridge_v1.py
bridgezoo/cablebridge/__init__.py
bridgezoo/cablebridge/cablebridge.py
bridgezoo/cablebridge/cablebridge_base.py
bridgezoo/cablebridge/cablebridge_models.py
bridgezoo/cablebridge/cablebridge_models_useless.py
bridgezoo/cablebridge/fem.py
test/test_env.py
test/test_parallel_env.py
bridgezoo-0.0.7.dist-info/LICENCE
bridgezoo-0.0.7.dist-info/METADATA
bridgezoo-0.0.7.dist-info/WHEEL
bridgezoo-0.0.7.dist-info/top_level.txt
bridgezoo-0.0.7.dist-info/RECORD
