Metadata-Version: 2.1
Name: bridgezoo
Version: 0.0.7
Summary: A Gymnasium style bridge environment.
Author-email: BillHu <billhu0228@icloud.com>
Maintainer-email: BillHu <billhu0228@icloud.com>
License: This software is under the MIT Licence
Project-URL: homepage, https://github.com/billhu0228/BridgeZOO
Project-URL: repository, https://github.com/billhu0228/BridgeZOO
License-File: LICENCE
Requires-Dist: pygame>=2.6.1
Requires-Dist: pettingzoo>=1.24.3
Requires-Dist: ezdxf>=1.3.4
Requires-Dist: openseespy>=3.5.0.0
